openlayer/__init__.py
openlayer/_base_client.py
openlayer/_client.py
openlayer/_compat.py
openlayer/_constants.py
openlayer/_exceptions.py
openlayer/_files.py
openlayer/_models.py
openlayer/_qs.py
openlayer/_resource.py
openlayer/_response.py
openlayer/_streaming.py
openlayer/_types.py
openlayer/_version.py
openlayer/py.typed
openlayer/_utils/__init__.py
openlayer/_utils/_compat.py
openlayer/_utils/_datetime_parse.py
openlayer/_utils/_json.py
openlayer/_utils/_logs.py
openlayer/_utils/_proxy.py
openlayer/_utils/_reflection.py
openlayer/_utils/_resources_proxy.py
openlayer/_utils/_streams.py
openlayer/_utils/_sync.py
openlayer/_utils/_transform.py
openlayer/_utils/_typing.py
openlayer/_utils/_utils.py
openlayer/lib/.keep
openlayer/lib/__init__.py
openlayer/lib/utils.py
openlayer/lib/core/__init__.py
openlayer/lib/core/base_model.py
openlayer/lib/core/metrics.py
openlayer/lib/core/tests.py
openlayer/lib/data/__init__.py
openlayer/lib/data/_upload.py
openlayer/lib/data/batch_inferences.py
openlayer/lib/data/commit.py
openlayer/lib/data/reference_dataset.py
openlayer/lib/guardrails/__init__.py
openlayer/lib/guardrails/base.py
openlayer/lib/integrations/__init__.py
openlayer/lib/integrations/anthropic_tracer.py
openlayer/lib/integrations/async_openai_tracer.py
openlayer/lib/integrations/bedrock_tracer.py
openlayer/lib/integrations/gemini_tracer.py
openlayer/lib/integrations/google_adk_tracer.py
openlayer/lib/integrations/groq_tracer.py
openlayer/lib/integrations/langchain_callback.py
openlayer/lib/integrations/litellm_tracer.py
openlayer/lib/integrations/mistral_tracer.py
openlayer/lib/integrations/oci_tracer.py
openlayer/lib/integrations/openai_agents.py
openlayer/lib/integrations/openai_tracer.py
openlayer/lib/tracing/__init__.py
openlayer/lib/tracing/context.py
openlayer/lib/tracing/enums.py
openlayer/lib/tracing/steps.py
openlayer/lib/tracing/tracer.py
openlayer/lib/tracing/traces.py
openlayer/resources/__init__.py
openlayer/resources/tests.py
openlayer-0.16.0.dist-info/METADATA
openlayer-0.16.0.dist-info/WHEEL
openlayer-0.16.0.dist-info/licenses/LICENSE
openlayer-0.16.0.dist-info/RECORD
