Metadata-Version: 2.3
Name: openlayer
Version: 0.16.0
Summary: The official Python library for the openlayer API
Project-URL: Homepage, https://github.com/openlayer-ai/openlayer-python
Project-URL: Repository, https://github.com/openlayer-ai/openlayer-python
Author-email: Openlayer <support@openlayer.com>
License: Apache-2.0
Classifier: Intended Audience :: Developers
Classifier: License :: OSI Approved :: Apache Software License
Classifier: Operating System :: MacOS
Classifier: Operating System :: Microsoft :: Windows
Classifier: Operating System :: OS Independent
Classifier: Operating System :: POSIX
Classifier: Operating System :: POSIX :: Linux
Classifier: Programming Language :: Python :: 3.9
Classifier: Programming Language :: Python :: 3.10
Classifier: Programming Language :: Python :: 3.11
Classifier: Programming Language :: Python :: 3.12
Classifier: Programming Language :: Python :: 3.13
Classifier: Programming Language :: Python :: 3.14
Classifier: Topic :: Software Development :: Libraries :: Python Modules
Classifier: Typing :: Typed
Requires-Python: >=3.9
Requires-Dist: anyio<5,>=3.5.0
Requires-Dist: distro<2,>=1.7.0
Requires-Dist: httpx<1,>=0.23.0
Requires-Dist: pandas; python_version >= '3.7'
Requires-Dist: pyarrow<=17.0.0,>=15.0.2; python_version == '3.8'
Requires-Dist: pyarrow>=18.0.0; python_version >= '3.9'
Requires-Dist: pydantic<3,>=1.9.0
Requires-Dist: pyyaml>=6.0
Requires-Dist: requests-toolbelt>=1.0.0
Requires-Dist: sniffio
Requires-Dist: tqdm
Requires-Dist: typing-extensions<5,>=4.10
Requires-Dist: wrapt>=1.14.0
Provides-Extra: aiohttp
Requires-Dist: aiohttp; extra == 'aiohttp'
Requires-Dist: httpx-aiohttp>=0.1.9; extra == 'aiohttp'
